{"config": {"view": {"continuousWidth": 300, "continuousHeight": 300}}, "data": {"name": "data-2ca09ffbd6ca8eed44892723a7219259"}, "mark": {"type": "bar"}, "encoding": {"color": {"condition": {"param": "param_42", "empty": false, "field": "Genre"}, "value": "lightgrey"}, "tooltip": [{"field": "Genre", "type": "nominal"}, {"field": "Count", "title": "Games in the Genre", "type": "quantitative"}], "x": {"field": "Count", "type": "quantitative"}, "y": {"field": "Genre", "type": "nominal"}}, "height": 500, "params": [{"name": "param_42", "select": {"type": "point", "fields": ["Genre"], "nearest": true, "on": "mouseover"}}], "width": 800, "$schema": "https://vega.github.io/schema/vega-lite/v5.15.1.json", "datasets": {"data-2ca09ffbd6ca8eed44892723a7219259": [{"Genre": "Action", "Count": 564}, {"Genre": "Adventure", "Count": 52}, {"Genre": "Educational", "Count": 5}, {"Genre": "Racing / Driving", "Count": 121}, {"Genre": "Role-Playing (RPG)", "Count": 103}, {"Genre": "Simulation", "Count": 80}, {"Genre": "Sports", "Count": 217}, {"Genre": "Strategy", "Count": 105}]}}